{
    "title": "IoGT CMS Manual v2.0",
    "folders": [
        {
            "title": "Introduction",
            "folderitems": [
                {
                    "title": "What is Wagtail?",
                    "url": "/cms-manual/intro/intro-to-wagtail/"
                },
                {
                    "title": "Signing into the CMS",
                    "url": "/cms-manual/intro/signing-in/"
                },
                {
                    "title": "Navigating the CMS",
                    "url": "/cms-manual/intro/navigating-wagtail/"
                },
                {
                    "title": "Search Functionality",
                    "url": "/cms-manual/intro/search-functionality/"
                },
                {
                    "title": "Reordering Pages",
                    "url": "/cms-manual/intro/reordering-pages/"
                }
            ]
        },
        {
            "title": "Creating Your Content",
            "folderitems": [
                {
                    "title": "Tips for content creation",
                    "url": "/cms-manual/content/tips/"
                },
                {
                    "title": "Call to Action!",
                    "url": "/cms-manual/content/call-to-action/"
                },
                {
                    "title": "Ease the user journey",
                    "url": "/cms-manual/content/user-journey/"
                },
                {
                    "title": "Creating Sections",
                    "url": "/cms-manual/content/sections/"
                },
                {
                    "title": "Changing Section color",
                    "url": "/cms-manual/content/section-colors/"
                },
                {
                    "title": "Homepage Banner",
                    "url": "/cms-manual/content/home-banner/"
                },
                {
                    "title": "Creating a footer Page",
                    "url": "/cms-manual/content/footer/"
                },
                {
                    "title": "Creating Polls",
                    "url": "/cms-manual/content/polls/"
                },
                {
                    "title": "Creating Article pages",
                    "url": "/cms-manual/content/articles/"
                },
                {
                    "title": "Editing existing pages",
                    "url": "/cms-manual/content/editing/"
                },
                {
                    "title": "The Promote Tab",
                    "url": "/cms-manual/content/promote/"
                },
                {
                    "title": "Automatic content rotation",
                    "url": "/cms-manual/content/auto-rotate/"
                },
                {
                    "title": "Recommended Settings",
                    "url": "/cms-manual/content/settings/"
                },
                {
                    "title": "Uploading and adding images",
                    "url": "/cms-manual/content/images/"
                },
                {
                    "title": "Adding languages",
                    "url": "/cms-manual/content/languages/"
                },
                {
                    "title": "Translating content",
                    "url": "/cms-manual/content/translate/"
                }
            ]
        },
        {
            "title": "Commenting",
            "folderitems": [
                {
                    "title": "Activating comments",
                    "url": "/cms-manual/comments/activating/"
                },
                {
                    "title": "Replying to comments",
                    "url": "/cms-manual/comments/replying/"
                },
                {
                    "title": "Deleting Comments",
                    "url": "/cms-manual/comments/deleting/"
                },
                {
                    "title": "Canned response",
                    "url": "/cms-manual/comments/canned/"
                },
                {
                    "title": "Reported Comments",
                    "url": "/cms-manual/comments/reporting/"
                },
                {
                    "title": "Moderation best practices",
                    "url": "/cms-manual/comments/moderation-tips/"
                },
                {
                    "title": "How to reply to messages, comments or user posts",
                    "url": "/cms-manual/comments/replying-messages-comments-posts/"
                },
                {
                    "title": "Handling trolls/vandalism on a Fan page",
                    "url": "/cms-manual/comments/trolls/"
                }
            ]
        },
        {
            "title": "Creating a Survey",
            "folderitems": [
                {
                    "title": "On the homepage",
                    "url": "/cms-manual/surveys/homepage-surveys/"
                },
                {
                    "title": "Create a survey in a particular content channel",
                    "url": "/cms-manual/surveys/creating/"
                },
                {
                    "title": "Allowing anonymous submissions to your surveys",
                    "url": "/cms-manual/surveys/anon-submissions/"
                },
                {
                    "title": "Different types of questions",
                    "url": "/cms-manual/surveys/question-types/"
                },
                {
                    "title": "Make survey appear in site footer",
                    "url": "/cms-manual/surveys/footer-surveys/"
                },
                {
                    "title": "Accessing survey results",
                    "url": "/cms-manual/surveys/accessing-results/"
                },
                {
                    "title": "Need More",
                    "url": "/cms-manual/surveys/need-more/"
                }
            ]
        }
    ]
}